CHANGES.txt
DEPENDENCIES.txt
README.txt
bootstrap.py
buildout.cfg
setup.py
src/ks/__init__.py
src/ks.mailersmtp.egg-info/PKG-INFO
src/ks.mailersmtp.egg-info/SOURCES.txt
src/ks.mailersmtp.egg-info/dependency_links.txt
src/ks.mailersmtp.egg-info/namespace_packages.txt
src/ks.mailersmtp.egg-info/not-zip-safe
src/ks.mailersmtp.egg-info/requires.txt
src/ks.mailersmtp.egg-info/top_level.txt
src/ks/mailersmtp/__init__.py
src/ks/mailersmtp/configure.zcml
src/ks/mailersmtp/interfaces.py
src/ks/mailersmtp/mailerannotation.py
src/ks/mailersmtp/mailersmtp.py
src/ks/mailersmtp/browser/__init__.py
src/ks/mailersmtp/browser/configure.zcml
src/ks/mailersmtp/etc/ks.mailersmtp-configure.zcml